Metadata-Version: 1.0
Name: sentencesplitterfortest
Version: 0.1
Summary: A Python library to split text into sentences.
Home-page: UNKNOWN
Author: Junyi Ye
Author-email: UNKNOWN
License: UNKNOWN
Platform: UNKNOWN
